LICENSE.txt
MANIFEST.in
README.md
requirements.txt
setup.cfg
setup.py
peace/__init__.py
peace/test.py
peace.egg-info/PKG-INFO
peace.egg-info/SOURCES.txt
peace.egg-info/dependency_links.txt
peace.egg-info/not-zip-safe
peace.egg-info/requires.txt
peace.egg-info/top_level.txt