Metadata-Version: 1.1
Name: peace
Version: 0.0.4
Summary: REST client
Home-page: https://bitbucket.org/garymonson/peace
Author: Gary Monson
Author-email: gary.monson@gmail.com
License: MIT
Keywords: rest client
Platform: UNKNOWN
Classifier: Development Status :: 3 - Alpha
Classifier: Intended Audience :: Developers
Classifier: Topic :: Internet :: WWW/HTTP
Classifier: Topic :: Software Development :: Libraries :: Python Modules
Classifier: License :: OSI Approved :: MIT License
Classifier: Programming Language :: Python :: 3
Classifier: Programming Language :: Python :: 3.4
